{
  "app-id": "io.github.weversonl.GnomeQuickShare",
  "runtime": "org.gnome.Platform",
  "runtime-version": "47",
  "sdk": "org.gnome.Sdk",
  "sdk-extensions": [
    "org.freedesktop.Sdk.Extension.rust-stable"
  ],
  "build-options": {
    "append-path": "/usr/lib/sdk/rust-stable/bin",
    "env": {
      "CARGO_NET_OFFLINE": "true"
    }
  },
  "command": "gnomeqs",
  "finish-args": [
    "--share=network",
    "--share=ipc",
    "--socket=wayland",
    "--socket=fallback-x11",
    "--device=dri",
    "--system-talk-name=org.bluez",
    "--talk-name=org.freedesktop.Notifications",
    "--filesystem=xdg-download"
  ],
  "modules": [
    {
      "name": "gnome-quick-share",
      "buildsystem": "simple",
      "build-commands": [
        "install -Dm644 cargo/config .cargo/config.toml",
        "meson setup --prefix=/app --buildtype=release _build",
        "ninja -j $FLATPAK_BUILDER_N_JOBS -C _build",
        "meson install -C _build"
      ],
      "sources": [
        {
          "type": "git",
          "url": "https://github.com/weversonl/gnome-quick-share.git",
          "commit": "99319a77c122f865ca0a0ba1b61a9b4fb0f20de1"
        },
        "cargo-sources.json"
      ]
    }
  ]
}
